<?xml version="1.0" encoding="UTF-8"?>
<objects serializationModel="Studio.02.02.00">
	<object class="MixerGroup" id="{d8a20c58-5fa8-4a82-b41c-5be2e58074d2}">
		<property name="name">
			<value>UI</value>
		</property>
		<relationship name="effectChain">
			<destination>{7c563baf-5fa8-424d-be47-6aa094d8bb2b}</destination>
		</relationship>
		<relationship name="panner">
			<destination>{d086c2ed-9a4d-4b1e-84d7-387dc91dd1fa}</destination>
		</relationship>
		<relationship name="output">
			<destination>{809dd9eb-b9cd-46e6-af78-7e211886bb57}</destination>
		</relationship>
	</object>
	<object class="MixerBusEffectChain" id="{7c563baf-5fa8-424d-be47-6aa094d8bb2b}">
		<relationship name="effects">
			<destination>{e42c8dfb-02d8-4f1c-9a20-16f0e88e7995}</destination>
			<destination>{d36964fb-9149-420b-bb09-f1700de710a8}</destination>
		</relationship>
	</object>
	<object class="MixerBusPanner" id="{d086c2ed-9a4d-4b1e-84d7-387dc91dd1fa}" />
	<object class="MixerBusFader" id="{e42c8dfb-02d8-4f1c-9a20-16f0e88e7995}" />
	<object class="SFXReverbEffect" id="{d36964fb-9149-420b-bb09-f1700de710a8}">
		<property name="decayTime">
			<value>1900</value>
		</property>
		<property name="earlyDelay">
			<value>46</value>
		</property>
		<property name="lateDelay">
			<value>55</value>
		</property>
		<property name="HFReference">
			<value>2600</value>
		</property>
		<property name="HFDecayRatio">
			<value>66</value>
		</property>
		<property name="diffusion">
			<value>76.5</value>
		</property>
		<property name="density">
			<value>85</value>
		</property>
		<property name="lowShelfFrequency">
			<value>270</value>
		</property>
		<property name="lowShelfGain">
			<value>-22.5</value>
		</property>
		<property name="earlyLateMix">
			<value>66</value>
		</property>
		<property name="wetLevel">
			<value>-21</value>
		</property>
	</object>
</objects>
